kikiutils_api/__init__.py
kikiutils_api/classes/__init__.py
kikiutils_api/classes/blacksheep.py
kikiutils_api/classes/sanic.py
kikiutils_api/classes/transmission.py
kikiutils_api/classes/websocket.py
kikiutils_api/decorators/__init__.py
kikiutils_api/decorators/blacksheep.py
kikiutils_api/decorators/sanic.py
kikiutils_api/utils/__init__.py
kikiutils_api/utils/blacksheep.py
kikiutils_api/utils/sanic.py
kiki_utils_api-1.6.0.dist-info/LICENSE.txt
kiki_utils_api-1.6.0.dist-info/METADATA
kiki_utils_api-1.6.0.dist-info/WHEEL
kiki_utils_api-1.6.0.dist-info/top_level.txt
kiki_utils_api-1.6.0.dist-info/zip-safe
kiki_utils_api-1.6.0.dist-info/RECORD
