Metadata-Version: 2.1
Name: kiki-utils-api
Version: 1.6.0
Summary: Utils functions with api data process.
Author: kiki-kanri
Author-email: a470666@gmail.com
Keywords: Utils
Classifier: License :: Freely Distributable
Requires-Python: >=3.8
License-File: LICENSE.txt
Requires-Dist: aiohttp[speedups]
Requires-Dist: kiki-utils
Requires-Dist: websockets
